pyprophet/__init__.py
pyprophet/_optimized.c
pyprophet/_optimized.so
pyprophet/classifiers.py
pyprophet/config.py
pyprophet/data_handling.py
pyprophet/main.py
pyprophet/main_helpers.py
pyprophet/optimized.py
pyprophet/pyprophet.py
pyprophet/report.py
pyprophet/semi_supervised.py
pyprophet/stats.py
pyprophet/std_logger.py
pyprophet/version.py
pyprophet-0.21.2.dist-info/DESCRIPTION.rst
pyprophet-0.21.2.dist-info/METADATA
pyprophet-0.21.2.dist-info/RECORD
pyprophet-0.21.2.dist-info/WHEEL
pyprophet-0.21.2.dist-info/entry_points.txt
pyprophet-0.21.2.dist-info/metadata.json
pyprophet-0.21.2.dist-info/top_level.txt
