Metadata-Version: 2.0
Name: pyprophet
Version: 0.21.2
Summary: Python reimplementation of mProphet peak scoring
Home-page: http://github.com/uweschmitt/pyprophet
Author: Uwe Schmitt
Author-email: rocksportrocker@gmail.com
License: BSD
Platform: UNKNOWN
Classifier: Development Status :: 3 - Alpha
Classifier: Environment :: Console
Classifier: Intended Audience :: Science/Research
Classifier: License :: OSI Approved :: BSD License
Classifier: Operating System :: OS Independent
Classifier: Topic :: Scientific/Engineering :: Bio-Informatics
Classifier: Topic :: Scientific/Engineering :: Chemistry
Requires-Dist: matplotlib
Requires-Dist: numexpr (>=2.1)
Requires-Dist: numpy (>=1.7.0)
Requires-Dist: pandas (>=0.13)
Requires-Dist: scikit-learn (>=0.17)
Requires-Dist: scipy (>=0.9.0)
Requires-Dist: seaborn
